rios_plc_test/__init__.py
rios_plc_test/cli.py
rios_plc_test-0.1.0.dist-info/METADATA
rios_plc_test-0.1.0.dist-info/WHEEL
rios_plc_test-0.1.0.dist-info/entry_points.txt
rios_plc_test-0.1.0.dist-info/top_level.txt
rios_plc_test-0.1.0.dist-info/RECORD
