Metadata-Version: 2.4
Name: rios-plc-test
Version: 0.1.0
Requires-Dist: pycomm3
